hudson/__init__.py
hudson/main.py
tests/__init__.py
tests/conftest.py
tests/test_main.py
tests/test_version.py
hudson-0.0.0a5.dist-info/LICENSE
hudson-0.0.0a5.dist-info/METADATA
hudson-0.0.0a5.dist-info/WHEEL
hudson-0.0.0a5.dist-info/top_level.txt
hudson-0.0.0a5.dist-info/RECORD
